<?xml version="1.0" encoding="UTF-8"?><record_update table="catalog_ui_policy_action">
    <catalog_ui_policy_action action="INSERT_OR_UPDATE">
        <catalog_item/>
        <catalog_variable>IO:b43ac9611b8f59108c5143f3cc4bcb9d</catalog_variable>
        <cleared>false</cleared>
        <disabled>ignore</disabled>
        <field/>
        <mandatory>false</mandatory>
        <order>100</order>
        <sys_class_name>catalog_ui_policy_action</sys_class_name>
        <sys_created_by>John.Schwab</sys_created_by>
        <sys_created_on>2022-11-14 19:58:02</sys_created_on>
        <sys_id>1b0670a71b8b55508c5143f3cc4bcbdf</sys_id>
        <sys_mod_count>0</sys_mod_count>
        <sys_name>person_leaving_variable_set</sys_name>
        <sys_package display_value="Termination Process Core" source="c5a5cfee1b9781108c5143f3cc4bcb64">c5a5cfee1b9781108c5143f3cc4bcb64</sys_package>
        <sys_policy/>
        <sys_scope display_value="Termination Process Core">c5a5cfee1b9781108c5143f3cc4bcb64</sys_scope>
        <sys_update_name>catalog_ui_policy_action_1b0670a71b8b55508c5143f3cc4bcbdf</sys_update_name>
        <sys_updated_by>John.Schwab</sys_updated_by>
        <sys_updated_on>2022-11-14 19:58:02</sys_updated_on>
        <table/>
        <ui_policy display_value="ifr not found">6fc53c671b8b55508c5143f3cc4bcb9e</ui_policy>
        <variable>person_leaving_variable_set</variable>
        <variable_set display_value="Individual Data">c737816d1b4f59108c5143f3cc4bcbf7</variable_set>
        <visible>false</visible>
    </catalog_ui_policy_action>
</record_update>
