<?xml version="1.0" encoding="UTF-8"?><record_update sys_domain="global" table="sys_decision_question">
    <sys_decision_question action="DELETE">
        <active>true</active>
        <answer>a3306b391b56155062e50ed2cd4bcbec</answer>
        <condition table="var__m_sys_decision_input_e2be9b711b56155062e50ed2cd4bcbfb">u_company=bcd6d4ac1ba1b010346ffd951a4bcb00^EQ<item display_table="core_company" display_value="Eastern Fire" endquery="false" field="u_company" goto="false" newquery="false" operator="=" or="false" value="bcd6d4ac1ba1b010346ffd951a4bcb00"/>
            <item endquery="true" field="" goto="false" newquery="false" operator="=" or="false" value=""/>
        </condition>
        <decision_table display_value="Company Number ERP and Payroll Lookup">e2be9b711b56155062e50ed2cd4bcbfb</decision_table>
        <default_answer>false</default_answer>
        <input_table>var__m_sys_decision_input_e2be9b711b56155062e50ed2cd4bcbfb</input_table>
        <label>Company ERP and Payroll Lookup_3100</label>
        <order>3100</order>
        <sys_class_name>sys_decision_question</sys_class_name>
        <sys_created_by>Terry.Lillo</sys_created_by>
        <sys_created_on>2022-10-03 15:19:46</sys_created_on>
        <sys_domain>global</sys_domain>
        <sys_domain_path>/</sys_domain_path>
        <sys_id>3db323b11b96155062e50ed2cd4bcbbf</sys_id>
        <sys_mod_count>1</sys_mod_count>
        <sys_name>Company ERP and Payroll Lookup_3100</sys_name>
        <sys_overrides/>
        <sys_package display_value="Termination Process Core" source="c5a5cfee1b9781108c5143f3cc4bcb64">c5a5cfee1b9781108c5143f3cc4bcb64</sys_package>
        <sys_policy/>
        <sys_scope display_value="Termination Process Core">c5a5cfee1b9781108c5143f3cc4bcb64</sys_scope>
        <sys_update_name>sys_decision_question_3db323b11b96155062e50ed2cd4bcbbf</sys_update_name>
        <sys_updated_by>Terry.Lillo</sys_updated_by>
        <sys_updated_on>2022-12-08 20:43:57</sys_updated_on>
    </sys_decision_question>
<sys_update_version action="INSERT_OR_UPDATE">
        <action>DELETE</action>
        <application display_value="Termination Process Core">c5a5cfee1b9781108c5143f3cc4bcb64</application>
        <file_path/>
        <instance_id>cb41202bdbe5d890601a11f8489619fb</instance_id>
        <instance_name>apigroup</instance_name>
        <name>sys_decision_question_3db323b11b96155062e50ed2cd4bcbbf</name>
        <payload><![CDATA[<?xml version="1.0" encoding="UTF-8"?><record_update sys_domain="global" table="sys_decision_question">
    <sys_decision_question action="INSERT_OR_UPDATE">
        <active>true</active>
        <answer>a3306b391b56155062e50ed2cd4bcbec</answer>
        <condition table="var__m_sys_decision_input_e2be9b711b56155062e50ed2cd4bcbfb">u_company=bcd6d4ac1ba1b010346ffd951a4bcb00^EQ<item display_table="core_company" display_value="Eastern Fire" endquery="false" field="u_company" goto="false" newquery="false" operator="=" or="false" value="bcd6d4ac1ba1b010346ffd951a4bcb00"/>
            <item endquery="true" field="" goto="false" newquery="false" operator="=" or="false" value=""/>
        </condition>
        <decision_table display_value="Company Number ERP and Payroll Lookup">e2be9b711b56155062e50ed2cd4bcbfb</decision_table>
        <default_answer>false</default_answer>
        <input_table>var__m_sys_decision_input_e2be9b711b56155062e50ed2cd4bcbfb</input_table>
        <label>Company ERP and Payroll Lookup_3100</label>
        <order>3100</order>
        <sys_class_name>sys_decision_question</sys_class_name>
        <sys_created_by>Terry.Lillo</sys_created_by>
        <sys_created_on>2022-10-03 15:19:46</sys_created_on>
        <sys_domain>global</sys_domain>
        <sys_domain_path>/</sys_domain_path>
        <sys_id>3db323b11b96155062e50ed2cd4bcbbf</sys_id>
        <sys_mod_count>1</sys_mod_count>
        <sys_name>Company ERP and Payroll Lookup_3100</sys_name>
        <sys_overrides/>
        <sys_package display_value="Termination Process Core" source="c5a5cfee1b9781108c5143f3cc4bcb64">c5a5cfee1b9781108c5143f3cc4bcb64</sys_package>
        <sys_policy/>
        <sys_scope display_value="Termination Process Core">c5a5cfee1b9781108c5143f3cc4bcb64</sys_scope>
        <sys_update_name>sys_decision_question_3db323b11b96155062e50ed2cd4bcbbf</sys_update_name>
        <sys_updated_by>Terry.Lillo</sys_updated_by>
        <sys_updated_on>2022-12-08 20:43:57</sys_updated_on>
    </sys_decision_question>
</record_update>]]></payload>
        <payload_hash>1424750377</payload_hash>
        <record_name>Company ERP and Payroll Lookup_3100</record_name>
        <reverted_from/>
        <source>c5a5cfee1b9781108c5143f3cc4bcb64</source>
        <source_table>sys_store_app</source_table>
        <state>previous</state>
        <sys_created_by>Terry.Lillo</sys_created_by>
        <sys_created_on>2023-10-06 14:40:52</sys_created_on>
        <sys_id>44e3ea10973979902e853cf3a253afc8</sys_id>
        <sys_mod_count>0</sys_mod_count>
        <sys_recorded_at>18b056f275d0000001</sys_recorded_at>
        <sys_updated_by>Terry.Lillo</sys_updated_by>
        <sys_updated_on>2023-10-06 14:40:52</sys_updated_on>
        <type>Decision</type>
        <update_guid>80e3ea10f839799028f6556e473c3fc8</update_guid>
        <update_guid_history>80e3ea10f839799028f6556e473c3fc8:0,32697543b0f76950ef0bc90079d48232:0,041d9976c5aaa1105b1d1ab8b6ad25a5:-1751445243,0a989dfea62aa11027226c99e420ca74:0,819c07570c0aa5d006088b8bff67acff:-2032721647,1e6f820b3e8ea11062707ca85d1ae271:1473086341,0464c1ed67ce2190604f7e07fd0817c3:1064846704,313449ad41ce219080a8eb2176b8f3c2:-2032721647,02d668d3e7ab991098e1909c0d3f1553:1473086341,4994456d5e479910d184fff4446ef4d3:1453803748,8c44852d044799105c0066e5f46dff7b:-1751445243,39b323b1eb961550859133b213f74dc2:967527662,432f015313a3d9904a28aad451bf50b9:0,2d283c5b5c6f99907924fdde47edd271:1473086341,747368c34d3e15506a4ace80d025cbb2:1453803748,b533e883923e1550a4aa1a2b28ac47be:-1751445243,7d33e883443e155047fcd27b327f7fba:-354511495</update_guid_history>
    </sys_update_version>
    <sys_metadata_delete action="INSERT_OR_UPDATE">
        <sys_audit_delete/>
        <sys_class_name>sys_metadata_delete</sys_class_name>
        <sys_created_by>Terry.Lillo</sys_created_by>
        <sys_created_on>2024-05-03 13:27:09</sys_created_on>
        <sys_db_object display_value="" name="sys_decision_question">sys_decision_question</sys_db_object>
        <sys_id>090f58462cad4ece827b176178c318c4</sys_id>
        <sys_metadata>3db323b11b96155062e50ed2cd4bcbbf</sys_metadata>
        <sys_mod_count>0</sys_mod_count>
        <sys_name>Company ERP and Payroll Lookup_3100</sys_name>
        <sys_package display_value="Termination Process Core" source="c5a5cfee1b9781108c5143f3cc4bcb64">c5a5cfee1b9781108c5143f3cc4bcb64</sys_package>
        <sys_parent/>
        <sys_policy/>
        <sys_scope display_value="Termination Process Core">c5a5cfee1b9781108c5143f3cc4bcb64</sys_scope>
        <sys_scope_delete display_value="">0372b18d7bd84de982a777fdeac3a4e1</sys_scope_delete>
        <sys_update_name>sys_decision_question_3db323b11b96155062e50ed2cd4bcbbf</sys_update_name>
        <sys_update_version display_value="sys_decision_question_3db323b11b96155062e50ed2cd4bcbbf">44e3ea10973979902e853cf3a253afc8</sys_update_version>
        <sys_updated_by>Terry.Lillo</sys_updated_by>
        <sys_updated_on>2024-05-03 13:27:09</sys_updated_on>
    </sys_metadata_delete>
</record_update>
